iceberg_seals.search-1.4-py3.5-nspkg.pth
iceberg_seals/search/predicting/__init__.py
iceberg_seals/search/predicting/predict_raster.py
iceberg_seals/search/predicting/predict_sealnet.py
iceberg_seals/search/tiling/__init__.py
iceberg_seals/search/tiling/tile_raster.py
iceberg_seals/search/utils/__init__.py
iceberg_seals/search/utils/model_library.py
iceberg_seals/search/utils/creators/__init__.py
iceberg_seals/search/utils/creators/create_trainingset.py
iceberg_seals/search/utils/custom_architectures/__init__.py
iceberg_seals/search/utils/custom_architectures/unet.py
iceberg_seals/search/utils/custom_architectures/unet_count_WRN.py
iceberg_seals/search/utils/custom_architectures/unet_count_WRN_occ_Dense.py
iceberg_seals/search/utils/custom_architectures/unet_occ_Dense.py
iceberg_seals/search/utils/dataloaders/__init__.py
iceberg_seals/search/utils/dataloaders/data_loader_test.py
iceberg_seals/search/utils/dataloaders/data_loader_train_count.py
iceberg_seals/search/utils/dataloaders/data_loader_train_det.py
iceberg_seals/search/utils/dataloaders/transforms_det.py
iceberg_seals/search/utils/dataloaders/transforms_det_resized.py
iceberg_seals/search/utils/visualizers/__init__.py
iceberg_seals/search/utils/visualizers/visualize_batch.py
iceberg_seals.search-1.4.data/scripts/iceberg_seals.predicting
iceberg_seals.search-1.4.data/scripts/iceberg_seals.tiling
iceberg_seals.search-1.4.dist-info/LICENSE.md
iceberg_seals.search-1.4.dist-info/METADATA
iceberg_seals.search-1.4.dist-info/WHEEL
iceberg_seals.search-1.4.dist-info/namespace_packages.txt
iceberg_seals.search-1.4.dist-info/top_level.txt
iceberg_seals.search-1.4.dist-info/RECORD
