Metadata-Version: 2.1
Name: iceberg-seals.search
Version: 1.4
Summary: The ICEBERG Seals usecase package
Home-page: https://www.github.com/iceberg-project/seals/
Author: ICEBERG Team
Author-email: iceberg-ci@googlegroups.com
License: MIT
Platform: UNKNOWN
Classifier: Development Status :: 1 - Planning
Classifier: Intended Audience :: Developers
Classifier: Environment :: Console
Classifier: Programming Language :: Python
Classifier: Programming Language :: Python :: 3
Classifier: Programming Language :: Python :: 3.5
Classifier: Topic :: Utilities
Classifier: Topic :: Scientific/Engineering
Classifier: Operating System :: MacOS :: MacOS X
Classifier: Operating System :: POSIX
Classifier: Operating System :: Unix
Requires-Dist: numpy
Requires-Dist: scipy
Requires-Dist: pandas
Requires-Dist: torch (==0.4.0)
Requires-Dist: torchvision (==0.2.1)
Requires-Dist: tensorboardX (==1.8)
Requires-Dist: opencv-python
Requires-Dist: rasterio
Requires-Dist: affine
Requires-Dist: geopandas
